{"cameraMode":{"drawMode":0,"name":"Shaded","section":"Shading Mode"},"sceneLighting":true,"audioPlay":false,"sceneViewState":{"m_AlwaysRefresh":false,"showFog":true,"showSkybox":true,"showFlares":true,"showImageEffects":true,"showParticleSystems":true,"showVisualEffectGraphs":true,"m_FxEnabled":true},"in2DMode":false,"pivot":{"x":12.365396499633789,"y":8.647228240966797,"z":23.23192024230957},"rotation":{"x":-0.012441430240869522,"y":-0.9771727919578552,"z":-0.05987515673041344,"w":0.20365044474601746},"size":1.4659581184387208,"orthographic":false}